fiber/__init__.py
fiber/client/__init__.py
fiber/client/tag.py
fiber/client/user.py
fiber/config.py
fiber/crud/__init__.py
fiber/crud/base.py
fiber/crud/contract.py
fiber/crud/tag.py
fiber/crud/user.py
fiber/models/__init__.py
fiber/models/contract.py
fiber/models/db.py
fiber/models/project.py
fiber/models/tag.py
fiber/models/user.py
fiber/schemas/__init__.py
fiber/schemas/orm/__init__.py
fiber/schemas/orm/base.py
fiber/schemas/orm/contract.py
fiber/schemas/orm/tag.py
fiber/schemas/orm/user.py
dsafe_fiber-0.1.0.dist-info/WHEEL
dsafe_fiber-0.1.0.dist-info/METADATA
dsafe_fiber-0.1.0.dist-info/RECORD
