Metadata-Version: 2.1
Name: dsafe-fiber
Version: 0.1.0
Summary: Smart Contract Monitoring SDK
License: MIT
Author: Robin Raymond
Author-email: robin@robinraymond.de
Requires-Python: >=3.9,<4.0
Classifier: License :: OSI Approved :: MIT License
Classifier: Programming Language :: Python :: 3
Classifier: Programming Language :: Python :: 3.9
Requires-Dist: SQLAlchemy (>=1.3.22,<2.0.0)
Requires-Dist: psycopg2-binary (>=2.8.6,<3.0.0)
Requires-Dist: pydantic (>=1.7.3,<2.0.0)
Requires-Dist: sqlalchemy-stubs (>=0.3,<0.4)
